sim/Sim.py
sim/SparkBIDS.py
sim/__init__.py
sim/spark_bids.py
simtools-0.2.dist-info/DESCRIPTION.rst
simtools-0.2.dist-info/METADATA
simtools-0.2.dist-info/RECORD
simtools-0.2.dist-info/WHEEL
simtools-0.2.dist-info/entry_points.txt
simtools-0.2.dist-info/metadata.json
simtools-0.2.dist-info/top_level.txt
